src/__init__.py
src/add_track_details.py
src/music_recommend.py
src/spotify_data.py
MUSIC_RECOMMENDATION-0.1.0.dist-info/METADATA
MUSIC_RECOMMENDATION-0.1.0.dist-info/WHEEL
MUSIC_RECOMMENDATION-0.1.0.dist-info/entry_points.txt
MUSIC_RECOMMENDATION-0.1.0.dist-info/top_level.txt
MUSIC_RECOMMENDATION-0.1.0.dist-info/RECORD
