Metadata-Version: 2.1
Name: MUSIC-RECOMMENDATION
Version: 0.1.0
Summary: A music recommendation system
Home-page: https://github.com/sayamiyaji/MUSIC_RECOMMENDATION.git
Author: SayaMiyaji
Author-email: s2222072@stu.musashino-u.ac.jp
License: UNKNOWN
Platform: UNKNOWN
Classifier: Programming Language :: Python :: 3
Classifier: License :: OSI Approved :: MIT License
Classifier: Operating System :: OS Independent
Requires-Python: >=3.6
Requires-Dist: Flask
Requires-Dist: pandas
Requires-Dist: scikit-learn
Requires-Dist: spotipy
Requires-Dist: gunicorn
